{"fields":[{"id":"gpslati"},{"id":"gpslong"},{"id":"nodeid"},{"id":"nodenm"},{"id":"nodeord"},{"id":"routenm"},{"id":"routetp"},{"id":"vehicleno"}],"records":[{"vehicleno":"대전75자9164","gpslati":"36.337378","routenm":"202","routetp":"간선버스","gpslong":"127.438391","nodenm":"대성여자고등학교","nodeord":"3","nodeid":"DJB8001365"},{"vehicleno":"대전75자9163","gpslati":"36.313883","routenm":"202","routetp":"간선버스","gpslong":"127.381743","nodenm":"도마네거리","nodeord":"17","nodeid":"DJB8001490"},{"vehicleno":"대전75자9160","gpslati":"36.29291","routenm":"202","routetp":"간선버스","gpslong":"127.320326","nodenm":"서대전IC","nodeord":"30","nodeid":"DJB8001944"},{"vehicleno":"대전75자3327","gpslati":"36.293049","routenm":"202","routetp":"간선버스","gpslong":"127.242551","nodenm":"신도농원","nodeord":"55","nodeid":"DJB8005187"},{"vehicleno":"대전75자3310","gpslati":"36.272257","routenm":"202","routetp":"간선버스","gpslong":"127.259279","nodenm":"노인종합복지관","nodeord":"74","nodeid":"DJB8005974"},{"vehicleno":"대전75자3377","gpslati":"36.307398","routenm":"202","routetp":"간선버스","gpslong":"127.364146","nodenm":"정림삼거리","nodeord":"98","nodeid":"DJB8002547"},{"vehicleno":"대전75자3370","gpslati":"36.337965","routenm":"202","routetp":"간선버스","gpslong":"127.429862","nodenm":"삼성네거리","nodeord":"115","nodeid":"DJB8001872"}]}